time/recordTime.py
juseokson123-1.0.1.dist-info/METADATA
juseokson123-1.0.1.dist-info/WHEEL
juseokson123-1.0.1.dist-info/top_level.txt
juseokson123-1.0.1.dist-info/RECORD
