Metadata-Version: 2.1
Name: juseokson123
Version: 1.0.1
Summary: record time
Home-page: http://github.com/snSon/abc
Download-URL: http://github.com/snSon/abc/
Author: sonjuseok
